win10ctypestoast/LICENSE
win10ctypestoast/README.MD
win10ctypestoast/__init__.py
win10ctypestoast/requirements.txt
win10ctypestoast/thirdparty.json
win10ctypestoast-0.10.dist-info/LICENSE.rst
win10ctypestoast-0.10.dist-info/METADATA
win10ctypestoast-0.10.dist-info/WHEEL
win10ctypestoast-0.10.dist-info/top_level.txt
win10ctypestoast-0.10.dist-info/RECORD
