Metadata-Version: 2.1
Name: win10ctypestoast
Version: 0.10
Summary: Windows-10-Toast-Notifications without pywin32 dependency
Home-page: https://github.com/hansalemaos/win10ctypestoast
Author: Johannes Fischer
Author-email: <aulasparticularesdealemaosp@gmail.com>
License: MIT
Keywords: ctypes,windows,toast
Classifier: Development Status :: 4 - Beta
Classifier: Programming Language :: Python :: 3 :: Only
Classifier: Programming Language :: Python :: 3.10
Classifier: Topic :: Scientific/Engineering :: Visualization
Classifier: Topic :: Software Development :: Libraries :: Python Modules
Classifier: Topic :: Utilities
License-File: LICENSE.rst
Requires-Dist: Pillow
Requires-Dist: pystray
